AUTHOR.txt
CHANGES.txt
LICENSE.txt
README.txt
bootstrap.py
buildout.cfg
setup.py
src/z3c/__init__.py
src/z3c.formdemo.egg-info/PKG-INFO
src/z3c.formdemo.egg-info/SOURCES.txt
src/z3c.formdemo.egg-info/dependency_links.txt
src/z3c.formdemo.egg-info/namespace_packages.txt
src/z3c.formdemo.egg-info/not-zip-safe
src/z3c.formdemo.egg-info/requires.txt
src/z3c.formdemo.egg-info/top_level.txt
src/z3c/formdemo/README.txt
src/z3c/formdemo/SETUP.cfg
src/z3c/formdemo/__init__.py
src/z3c/formdemo/application.zcml
src/z3c/formdemo/configure.zcml
src/z3c/formdemo/ftesting.zcml
src/z3c/formdemo/i18n.py
src/z3c/formdemo/layer.py
src/z3c/formdemo/testing.py
src/z3c/formdemo/tests.py
src/z3c/formdemo/z3c.formdemo-configure.zcml
src/z3c/formdemo/addressbook/README.txt
src/z3c/formdemo/addressbook/__init__.py
src/z3c/formdemo/addressbook/address.pt
src/z3c/formdemo/addressbook/addressbook.css
src/z3c/formdemo/addressbook/addressbook.pt
src/z3c/formdemo/addressbook/addresses.pt
src/z3c/formdemo/addressbook/browser.py
src/z3c/formdemo/addressbook/configure.zcml
src/z3c/formdemo/addressbook/contact.pt
src/z3c/formdemo/addressbook/contact.py
src/z3c/formdemo/addressbook/dateselect.pt
src/z3c/formdemo/addressbook/dateselect.py
src/z3c/formdemo/addressbook/email.pt
src/z3c/formdemo/addressbook/emails.pt
src/z3c/formdemo/addressbook/form-macros.pt
src/z3c/formdemo/addressbook/interfaces.py
src/z3c/formdemo/addressbook/phone.pt
src/z3c/formdemo/addressbook/phones.pt
src/z3c/formdemo/addressbook/text-shadow.js
src/z3c/formdemo/browser/__init__.py
src/z3c/formdemo/browser/configure.zcml
src/z3c/formdemo/browser/formatter.py
src/z3c/formdemo/browser/index.pt
src/z3c/formdemo/browser/table_sorted_header.pt
src/z3c/formdemo/calculator/README.txt
src/z3c/formdemo/calculator/__init__.py
src/z3c/formdemo/calculator/browser.py
src/z3c/formdemo/calculator/calculator.css
src/z3c/formdemo/calculator/calculator.pt
src/z3c/formdemo/calculator/configure.zcml
src/z3c/formdemo/message/README.txt
src/z3c/formdemo/message/__init__.py
src/z3c/formdemo/message/browser.py
src/z3c/formdemo/message/configure.zcml
src/z3c/formdemo/message/display.pt
src/z3c/formdemo/message/interfaces.py
src/z3c/formdemo/message/message.py
src/z3c/formdemo/message/what-values.csv
