Metadata-Version: 1.0
Name: z3c.formdemo
Version: 1.5.6
Summary: A set of demo applications for z3c.form and z3c.formui
Home-page: http://pypi.python.org/pypi/z3c.formdemo
Author: Stephan Richter, Roger Ineichen and the Zope Community
Author-email: zope-dev@zope.org
License: ZPL 2.1
Keywords: zope3 form widget
Platform: UNKNOWN
Classifier: Development Status :: 5 - Production/Stable
Classifier: Environment :: Web Environment
Classifier: Intended Audience :: Developers
Classifier: License :: OSI Approved :: Zope Public License
Classifier: Programming Language :: Python
Classifier: Natural Language :: English
Classifier: Operating System :: OS Independent
Classifier: Topic :: Internet :: WWW/HTTP
Classifier: Framework :: Zope3
